connic/__init__.py
connic/cli.py
connic/core.py
connic/loader.py
connic/tools.py
connic_composer_sdk-0.1.0.dist-info/licenses/LICENSE
connic_composer_sdk-0.1.0.dist-info/METADATA
connic_composer_sdk-0.1.0.dist-info/WHEEL
connic_composer_sdk-0.1.0.dist-info/entry_points.txt
connic_composer_sdk-0.1.0.dist-info/top_level.txt
connic_composer_sdk-0.1.0.dist-info/RECORD
