Metadata-Version: 2.4
Name: connic-composer-sdk
Version: 0.1.0
Summary: The Connic Composer SDK for building agents and enterprise-level tools.
Author-email: Connic Team <hello@connic.co>
Classifier: Programming Language :: Python :: 3
Classifier: Programming Language :: Python :: 3.10
Classifier: Programming Language :: Python :: 3.11
Classifier: Programming Language :: Python :: 3.12
Classifier: License :: OSI Approved :: MIT License
Classifier: Operating System :: OS Independent
Classifier: Development Status :: 4 - Beta
Classifier: Intended Audience :: Developers
Classifier: Topic :: Software Development :: Libraries :: Python Modules
Requires-Python: >=3.10
License-File: LICENSE
Requires-Dist: click>=8.0.0
Requires-Dist: pyyaml>=6.0
Requires-Dist: pydantic>=2.0.0
Requires-Dist: watchdog>=3.0.0
Requires-Dist: nats-py>=2.7.0
Requires-Dist: httpx>=0.25.0
Requires-Dist: websockets>=12.0
Provides-Extra: dev
Requires-Dist: pytest; extra == "dev"
Requires-Dist: ruff; extra == "dev"
Dynamic: license-file
